sdv_installer/__init__.py
sdv_installer/config.py
sdv_installer/constants.py
sdv_installer/authentication/__init__.py
sdv_installer/authentication/authentication.py
sdv_installer/cli/__init__.py
sdv_installer/cli/__main__.py
sdv_installer/installation/__init__.py
sdv_installer/installation/installer.py
sdv_installer/utils/__init__.py
sdv_installer/utils/console_utils.py
sdv_installer/utils/data_storage.py
sdv_installer/utils/package_utils.py
sdv_installer/utils/request_error_handling.py
sdv_installer/utils/system_requirements.py
sdv_installer-0.2.0.dist-info/licenses/LICENSE
sdv_installer-0.2.0.dist-info/METADATA
sdv_installer-0.2.0.dist-info/WHEEL
sdv_installer-0.2.0.dist-info/entry_points.txt
sdv_installer-0.2.0.dist-info/top_level.txt
sdv_installer-0.2.0.dist-info/RECORD
