Metadata-Version: 2.4
Name: sdv-installer
Version: 0.2.0
Summary: Package to install SDV Enterprise packages.
Author-email: "DataCebo, Inc." <info@datacebo.com>
License: MIT
Keywords: sdv,synthetic-data,synthetic-data-generation,timeseries,single-table,multi-table
Classifier: Development Status :: 1 - Planning
Classifier: Intended Audience :: Developers
Classifier: License :: Free for non-commercial use
Classifier: Natural Language :: English
Classifier: Programming Language :: Python :: 3
Classifier: Programming Language :: Python :: 3.9
Classifier: Programming Language :: Python :: 3.10
Classifier: Programming Language :: Python :: 3.11
Classifier: Programming Language :: Python :: 3.12
Classifier: Programming Language :: Python :: 3.13
Classifier: Topic :: Scientific/Engineering :: Artificial Intelligence
Requires-Python: <3.14,>=3.9
License-File: LICENSE
Requires-Dist: requests
Requires-Dist: platformdirs
Requires-Dist: pip>=22.3
Requires-Dist: packaging
Provides-Extra: test
Requires-Dist: pytest; extra == "test"
Requires-Dist: invoke; extra == "test"
Requires-Dist: packaging; extra == "test"
Provides-Extra: dev
Requires-Dist: pip>=9.0.1; extra == "dev"
Requires-Dist: pytest; extra == "dev"
Requires-Dist: invoke; extra == "dev"
Requires-Dist: bump-my-version>=0.18.3; extra == "dev"
Requires-Dist: ruff>=0.7.1; extra == "dev"
Requires-Dist: twine<4,>=1.10.0; extra == "dev"
Requires-Dist: wheel>=0.30.0; extra == "dev"
Requires-Dist: coverage; extra == "dev"
Requires-Dist: tomli; extra == "dev"
Dynamic: license-file
